kusso_django/__init__.py
kusso_django/kusso/__init__.py
kusso_django/kusso/migrations/0001_initial.py
kusso_django/kusso/migrations/__init__.py
kusso_django/kusso/models.py
kusso_django/kusso/urls.py
kusso_django/kusso/views.py
kusso_django-1.1.6.dist-info/LICENSE
kusso_django-1.1.6.dist-info/METADATA
kusso_django-1.1.6.dist-info/WHEEL
kusso_django-1.1.6.dist-info/RECORD
