Metadata-Version: 2.1
Name: kusso-django
Version: 1.1.6
Summary: Django app for KU SSO authentication
Home-page: https://gitlab.com/cjaikaeo/kusso-django
License: BSD 2-clause
Author: Chaiporn Jaikaeo
Author-email: chaiporn.j@ku.ac.th
Requires-Python: >=3.6,<4.0
Classifier: License :: Other/Proprietary License
Classifier: Programming Language :: Python :: 3
Classifier: Programming Language :: Python :: 3.6
Classifier: Programming Language :: Python :: 3.7
Classifier: Programming Language :: Python :: 3.8
Classifier: Programming Language :: Python :: 3.9
Classifier: Programming Language :: Python :: 3.10
Classifier: Programming Language :: Python :: 3.11
Classifier: Programming Language :: Python :: 3.12
Requires-Dist: AuthLib (>=1.2,<2.0)
Requires-Dist: requests (>=2.27,<3.0)
